nest_reset/__init__.py
nest_reset/__main__.py
nest_reset/cli.py
nest_reset/nest_reset.py
nest_reset-0.1.3.dist-info/LICENSE
nest_reset-0.1.3.dist-info/METADATA
nest_reset-0.1.3.dist-info/WHEEL
nest_reset-0.1.3.dist-info/entry_points.txt
nest_reset-0.1.3.dist-info/top_level.txt
nest_reset-0.1.3.dist-info/RECORD
