Metadata-Version: 2.1
Name: nest-reset
Version: 0.1.3
Summary: Simple CLI tool to listen for changes in NEST thermostat and reset the temperature back
Home-page: https://github.com/viseshrp/nest_reset
Author: Visesh Prasad
Author-email: viseshrprasad@gmail.com
License: MIT license
Keywords: nest_reset nest nest-reset
Platform: UNKNOWN
Classifier: Development Status :: 4 - Beta
Classifier: Environment :: Console
Classifier: Intended Audience :: Developers
Classifier: License :: OSI Approved :: MIT License
Classifier: Operating System :: OS Independent
Classifier: Natural Language :: English
Classifier: Programming Language :: Python :: 2
Classifier: Programming Language :: Python :: 2.7
Classifier: Programming Language :: Python :: 3
Classifier: Programming Language :: Python :: 3.4
Classifier: Programming Language :: Python :: 3.5
Classifier: Programming Language :: Python :: 3.6
Classifier: Programming Language :: Python :: 3.7
Classifier: Topic :: Software Development :: Libraries :: Python Modules
Requires-Python: >=2.7
Requires-Dist: future (>=0.15.2)
Requires-Dist: Click (>=6.0)
Requires-Dist: python-nest (==4.0.5)
